gpu/__init__.py
gpu/gpu.py
gpu_info_shnu-0.6.1.dist-info/LICENSE
gpu_info_shnu-0.6.1.dist-info/METADATA
gpu_info_shnu-0.6.1.dist-info/WHEEL
gpu_info_shnu-0.6.1.dist-info/top_level.txt
gpu_info_shnu-0.6.1.dist-info/RECORD
