Metadata-Version: 2.1
Name: gpu-info-shnu
Version: 0.6.1
Summary: Detect GPU
Home-page: https://www.shnu.edu.cn
Author: Prof.Luqun Li
Author-email: liluqun@gmail.com
License: UNKNOWN
Project-URL: Bug Tracker, https://www.shnu.edu.cn
Platform: UNKNOWN
Classifier: Programming Language :: Python :: 3
Classifier: License :: OSI Approved :: MIT License
Classifier: Operating System :: OS Independent
Requires-Python: >=3.6
License-File: LICENSE
